LICENSE
MANIFEST.in
README.md
setup.json
setup.py
rlgym/rocket_league/README.md
rlgym/rocket_league/__init__.py
rlgym/rocket_league/common_values.py
rlgym/rocket_league/math.py
rlgym/rocket_league/version.py
rlgym/rocket_league/action_parsers/__init__.py
rlgym/rocket_league/action_parsers/lookup_table_action.py
rlgym/rocket_league/action_parsers/repeat_action.py
rlgym/rocket_league/api/__init__.py
rlgym/rocket_league/api/car.py
rlgym/rocket_league/api/game_config.py
rlgym/rocket_league/api/game_state.py
rlgym/rocket_league/api/physics_object.py
rlgym/rocket_league/api/utils.py
rlgym/rocket_league/done_conditions/__init__.py
rlgym/rocket_league/done_conditions/all_condition.py
rlgym/rocket_league/done_conditions/any_condition.py
rlgym/rocket_league/done_conditions/goal_condition.py
rlgym/rocket_league/done_conditions/no_touch_condition.py
rlgym/rocket_league/done_conditions/noop_condition.py
rlgym/rocket_league/done_conditions/timeout_condition.py
rlgym/rocket_league/obs_builders/__init__.py
rlgym/rocket_league/obs_builders/default_obs.py
rlgym/rocket_league/reward_functions/__init__.py
rlgym/rocket_league/reward_functions/combined_reward.py
rlgym/rocket_league/reward_functions/goal_reward.py
rlgym/rocket_league/reward_functions/touch_reward.py
rlgym/rocket_league/rlviser/__init__.py
rlgym/rocket_league/rlviser/rlviser_renderer.py
rlgym/rocket_league/sim/__init__.py
rlgym/rocket_league/sim/rocketsim_engine.py
rlgym/rocket_league/sim/collision_meshes/soccar/mesh_0.cmf
rlgym/rocket_league/sim/collision_meshes/soccar/mesh_1.cmf
rlgym/rocket_league/sim/collision_meshes/soccar/mesh_10.cmf
rlgym/rocket_league/sim/collision_meshes/soccar/mesh_11.cmf
rlgym/rocket_league/sim/collision_meshes/soccar/mesh_12.cmf
rlgym/rocket_league/sim/collision_meshes/soccar/mesh_13.cmf
rlgym/rocket_league/sim/collision_meshes/soccar/mesh_14.cmf
rlgym/rocket_league/sim/collision_meshes/soccar/mesh_15.cmf
rlgym/rocket_league/sim/collision_meshes/soccar/mesh_2.cmf
rlgym_rocket_league.egg-info/PKG-INFO
rlgym_rocket_league.egg-info/SOURCES.txt
rlgym_rocket_league.egg-info/dependency_links.txt
rlgym_rocket_league.egg-info/requires.txt
rlgym_rocket_league.egg-info/top_level.txt