Metadata-Version: 2.1
Name: rlgym-rocket-league
Version: 2.0.1
Summary: A python API that can be used to treat the game Rocket League as a Gym-like environment for Reinforcement Learning projects.
Home-page: https://rlgym.org
Author: Lucas Emery, Matthew Allen and Rolv-Arild Braaten
Author-email: contact@rlgym.org
License: Apache 2.0
Project-URL: Source Code, https://github.com/lucas-emery/rocket-league-gym
Keywords: rocket-league,gym,reinforcement-learning,rlgym
Classifier: Development Status :: 5 - Production/Stable
Classifier: License :: OSI Approved :: Apache Software License
Classifier: Programming Language :: Python :: 3
Classifier: Operating System :: OS Independent
Requires-Python: >=3.7
Provides-Extra: sim
Provides-Extra: rlviser
Provides-Extra: all
License-File: LICENSE
